{
  "11761284": {
    "exists": true,
    "notFound": false,
    "closed": false,
    "cnt": 339
  },
  "12869641": {
    "exists": true,
    "notFound": false,
    "closed": false,
    "cnt": 0
  },
  "12886594": {
    "exists": true,
    "notFound": false,
    "closed": false,
    "cnt": 0
  },
  "13489796": {
    "exists": true,
    "notFound": false,
    "closed": false,
    "cnt": 4
  },
  "18086526": {
    "exists": true,
    "notFound": false,
    "closed": false,
    "cnt": 0
  },
  "18090568": {
    "exists": true,
    "notFound": false,
    "closed": false,
    "cnt": 370
  },
  "18277255": {
    "exists": true,
    "notFound": false,
    "closed": false,
    "cnt": 0
  },
  "18277606": {
    "exists": true,
    "notFound": false,
    "closed": false,
    "cnt": 3513
  },
  "18277875": {
    "exists": true,
    "notFound": false,
    "closed": false,
    "cnt": 4
  },
  "18278376": {
    "exists": true,
    "notFound": false,
    "closed": false,
    "cnt": 1154
  },
  "18290263": {
    "exists": true,
    "notFound": false,
    "closed": false,
    "cnt": 2038
  },
  "19212851": {
    "exists": true,
    "notFound": false,
    "closed": false,
    "cnt": 0
  },
  "19360996": {
    "exists": true,
    "notFound": false,
    "closed": false,
    "cnt": 229
  },
  "21227525": {
    "exists": true,
    "notFound": false,
    "closed": false,
    "cnt": 0
  },
  "21584164": {
    "exists": true,
    "notFound": false,
    "closed": false,
    "cnt": 0
  },
  "21730256": {
    "exists": true,
    "notFound": false,
    "closed": false,
    "cnt": 0
  },
  "30820508": {
    "exists": true,
    "notFound": false,
    "closed": false,
    "cnt": 0
  },
  "35812352": {
    "exists": true,
    "notFound": false,
    "closed": false,
    "cnt": 0
  },
  "35861675": {
    "exists": true,
    "notFound": false,
    "closed": false,
    "cnt": 12451
  },
  "36286222": {
    "exists": true,
    "notFound": false,
    "closed": false,
    "cnt": 160
  },
  "36459188": {
    "exists": true,
    "notFound": false,
    "closed": false,
    "cnt": 0
  },
  "36628969": {
    "exists": true,
    "notFound": false,
    "closed": false,
    "cnt": 0
  },
  "36982710": {
    "exists": true,
    "notFound": false,
    "closed": false,
    "cnt": 71
  },
  "37060368": {
    "exists": true,
    "notFound": false,
    "closed": false,
    "cnt": 1066
  },
  "37336568": {
    "exists": true,
    "notFound": false,
    "closed": false,
    "cnt": 4936
  },
  "37362475": {
    "exists": true,
    "notFound": false,
    "closed": false,
    "cnt": 596
  },
  "37396091": {
    "exists": true,
    "notFound": false,
    "closed": false,
    "cnt": 0
  },
  "37484701": {
    "exists": true,
    "notFound": false,
    "closed": false,
    "cnt": 535
  },
  "38229148": {
    "exists": true,
    "notFound": false,
    "closed": false,
    "cnt": 115
  },
  "38711317": {
    "exists": true,
    "notFound": false,
    "closed": false,
    "cnt": 0
  },
  "67458921": {
    "exists": true,
    "notFound": false,
    "closed": false,
    "cnt": 562
  },
  "78231087": {
    "exists": true,
    "notFound": false,
    "closed": false,
    "cnt": 0
  },
  "571520022": {
    "exists": true,
    "notFound": false,
    "closed": false,
    "cnt": 361
  },
  "1001246778": {
    "exists": true,
    "notFound": false,
    "closed": false,
    "cnt": 278
  },
  "1002278593": {
    "exists": true,
    "notFound": false,
    "closed": false,
    "cnt": 492
  },
  "1018150030": {
    "exists": true,
    "notFound": false,
    "closed": false,
    "cnt": 729
  },
  "1018296190": {
    "exists": true,
    "notFound": false,
    "closed": false,
    "cnt": 0
  },
  "1020371113": {
    "exists": true,
    "notFound": false,
    "closed": false,
    "cnt": 0
  },
  "1030300995": {
    "exists": true,
    "notFound": false,
    "closed": false,
    "cnt": 919
  },
  "1036097404": {
    "exists": true,
    "notFound": false,
    "closed": false,
    "cnt": 17
  },
  "1042819747": {
    "exists": true,
    "notFound": false,
    "closed": false,
    "cnt": 0
  },
  "1047391877": {
    "exists": true,
    "notFound": false,
    "closed": false,
    "cnt": 0
  },
  "1054901205": {
    "exists": true,
    "notFound": false,
    "closed": false,
    "cnt": 2974
  },
  "1058358770": {
    "exists": true,
    "notFound": false,
    "closed": false,
    "cnt": 330
  },
  "1064966222": {
    "exists": true,
    "notFound": false,
    "closed": false,
    "cnt": 0
  },
  "1068711518": {
    "exists": true,
    "notFound": false,
    "closed": false,
    "cnt": 607
  },
  "1085363825": {
    "exists": true,
    "notFound": false,
    "closed": false,
    "cnt": 262
  },
  "1087269169": {
    "exists": true,
    "notFound": false,
    "closed": false,
    "cnt": 164
  },
  "1092491695": {
    "exists": true,
    "notFound": false,
    "closed": false,
    "cnt": 0
  },
  "1093956988": {
    "exists": true,
    "notFound": false,
    "closed": false,
    "cnt": 64
  },
  "1102755370": {
    "exists": true,
    "notFound": false,
    "closed": false,
    "cnt": 0
  },
  "1104270647": {
    "exists": true,
    "notFound": false,
    "closed": false,
    "cnt": 742
  },
  "1112677796": {
    "exists": true,
    "notFound": false,
    "closed": false,
    "cnt": 183
  },
  "1113922256": {
    "exists": true,
    "notFound": false,
    "closed": false,
    "cnt": 491
  },
  "1117348903": {
    "exists": true,
    "notFound": false,
    "closed": false,
    "cnt": 759
  },
  "1117990870": {
    "exists": true,
    "notFound": false,
    "closed": false,
    "cnt": 0
  },
  "1123951602": {
    "exists": true,
    "notFound": false,
    "closed": false,
    "cnt": 0
  },
  "1124089778": {
    "exists": true,
    "notFound": false,
    "closed": false,
    "cnt": 118
  },
  "1146915665": {
    "exists": true,
    "notFound": false,
    "closed": false,
    "cnt": 179
  },
  "1150175543": {
    "exists": true,
    "notFound": false,
    "closed": false,
    "cnt": 65
  },
  "1159240671": {
    "exists": true,
    "notFound": false,
    "closed": false,
    "cnt": 702
  },
  "1160736179": {
    "exists": true,
    "notFound": false,
    "closed": false,
    "cnt": 588
  },
  "1160913545": {
    "exists": true,
    "notFound": false,
    "closed": false,
    "cnt": 548
  },
  "1165327961": {
    "exists": true,
    "notFound": false,
    "closed": false,
    "cnt": 0
  },
  "1168242083": {
    "exists": true,
    "notFound": false,
    "closed": false,
    "cnt": 394
  },
  "1171842723": {
    "exists": true,
    "notFound": false,
    "closed": false,
    "cnt": 8
  },
  "1175185595": {
    "exists": true,
    "notFound": false,
    "closed": false,
    "cnt": 302
  },
  "1181842478": {
    "exists": true,
    "notFound": false,
    "closed": false,
    "cnt": 36
  },
  "1196398020": {
    "exists": true,
    "notFound": false,
    "closed": false,
    "cnt": 603
  },
  "1205074933": {
    "exists": true,
    "notFound": false,
    "closed": false,
    "cnt": 0
  },
  "1205594755": {
    "exists": true,
    "notFound": false,
    "closed": false,
    "cnt": 44
  },
  "1216066235": {
    "exists": true,
    "notFound": false,
    "closed": false,
    "cnt": 838
  },
  "1222386087": {
    "exists": true,
    "notFound": false,
    "closed": false,
    "cnt": 0
  },
  "1227687954": {
    "exists": true,
    "notFound": false,
    "closed": false,
    "cnt": 208
  },
  "1247941459": {
    "exists": true,
    "notFound": false,
    "closed": false,
    "cnt": 0
  },
  "1255380075": {
    "exists": true,
    "notFound": false,
    "closed": false,
    "cnt": 358
  },
  "1255937775": {
    "exists": true,
    "notFound": false,
    "closed": false,
    "cnt": 1247
  },
  "1258821325": {
    "exists": true,
    "notFound": false,
    "closed": false,
    "cnt": 1002
  },
  "1259468697": {
    "exists": true,
    "notFound": false,
    "closed": false,
    "cnt": 0
  },
  "1260711461": {
    "exists": true,
    "notFound": false,
    "closed": false,
    "cnt": 1
  },
  "1262214960": {
    "exists": true,
    "notFound": false,
    "closed": false,
    "cnt": 137
  },
  "1262874028": {
    "exists": true,
    "notFound": false,
    "closed": false,
    "cnt": 0
  },
  "1265438527": {
    "exists": true,
    "notFound": false,
    "closed": false,
    "cnt": 0
  },
  "1269943699": {
    "exists": true,
    "notFound": false,
    "closed": false,
    "cnt": 72
  },
  "1274642038": {
    "exists": true,
    "notFound": false,
    "closed": false,
    "cnt": 1864
  },
  "1285315529": {
    "exists": true,
    "notFound": false,
    "closed": false,
    "cnt": 0
  },
  "1285873777": {
    "exists": true,
    "notFound": false,
    "closed": false,
    "cnt": 9
  },
  "1289603188": {
    "exists": true,
    "notFound": false,
    "closed": false,
    "cnt": 0
  },
  "1316724095": {
    "exists": true,
    "notFound": false,
    "closed": false,
    "cnt": 936
  },
  "1320473224": {
    "exists": true,
    "notFound": false,
    "closed": false,
    "cnt": 221
  },
  "1321262202": {
    "exists": true,
    "notFound": false,
    "closed": false,
    "cnt": 0
  },
  "1334322058": {
    "exists": true,
    "notFound": false,
    "closed": false,
    "cnt": 13
  },
  "1336107234": {
    "exists": true,
    "notFound": false,
    "closed": false,
    "cnt": 0
  },
  "1340256639": {
    "exists": true,
    "notFound": false,
    "closed": false,
    "cnt": 84
  },
  "1344725313": {
    "exists": true,
    "notFound": false,
    "closed": false,
    "cnt": 446
  },
  "1345903392": {
    "exists": true,
    "notFound": false,
    "closed": false,
    "cnt": 0
  },
  "1360567397": {
    "exists": true,
    "notFound": false,
    "closed": false,
    "cnt": 454
  },
  "1365600158": {
    "exists": true,
    "notFound": false,
    "closed": false,
    "cnt": 0
  },
  "1367329589": {
    "exists": true,
    "notFound": false,
    "closed": false,
    "cnt": 693
  },
  "1390422996": {
    "exists": true,
    "notFound": false,
    "closed": false,
    "cnt": 10
  },
  "1391357756": {
    "exists": true,
    "notFound": false,
    "closed": false,
    "cnt": 0
  },
  "1402872861": {
    "exists": true,
    "notFound": false,
    "closed": false,
    "cnt": 1
  },
  "1405109689": {
    "exists": true,
    "notFound": false,
    "closed": false,
    "cnt": 397
  },
  "1407375029": {
    "exists": true,
    "notFound": false,
    "closed": false,
    "cnt": 266
  },
  "1414869686": {
    "exists": true,
    "notFound": false,
    "closed": false,
    "cnt": 14
  },
  "1415321222": {
    "exists": true,
    "notFound": false,
    "closed": false,
    "cnt": 0
  },
  "1424835754": {
    "exists": true,
    "notFound": false,
    "closed": false,
    "cnt": 2099
  },
  "1436548595": {
    "exists": true,
    "notFound": false,
    "closed": false,
    "cnt": 0
  },
  "1477220900": {
    "exists": true,
    "notFound": false,
    "closed": false,
    "cnt": 0
  },
  "1479355246": {
    "exists": true,
    "notFound": false,
    "closed": false,
    "cnt": 1054
  },
  "1481541595": {
    "exists": true,
    "notFound": false,
    "closed": false,
    "cnt": 9
  },
  "1482683542": {
    "exists": true,
    "notFound": false,
    "closed": false,
    "cnt": 0
  },
  "1493959618": {
    "exists": true,
    "notFound": false,
    "closed": false,
    "cnt": 101
  },
  "1499098228": {
    "exists": true,
    "notFound": false,
    "closed": false,
    "cnt": 1
  },
  "1500645916": {
    "exists": true,
    "notFound": false,
    "closed": false,
    "cnt": 179
  },
  "1504098064": {
    "exists": true,
    "notFound": false,
    "closed": false,
    "cnt": 0
  },
  "1511279042": {
    "exists": true,
    "notFound": false,
    "closed": false,
    "cnt": 57
  },
  "1512085123": {
    "exists": true,
    "notFound": false,
    "closed": false,
    "cnt": 140
  },
  "1550266134": {
    "exists": true,
    "notFound": false,
    "closed": false,
    "cnt": 0
  },
  "1550970127": {
    "exists": true,
    "notFound": false,
    "closed": false,
    "cnt": 24
  },
  "1559080868": {
    "exists": true,
    "notFound": false,
    "closed": false,
    "cnt": 0
  },
  "1562809784": {
    "exists": true,
    "notFound": false,
    "closed": false,
    "cnt": 795
  },
  "1563722647": {
    "exists": true,
    "notFound": false,
    "closed": false,
    "cnt": 74
  },
  "1567294388": {
    "exists": true,
    "notFound": false,
    "closed": false,
    "cnt": 8
  },
  "1569255610": {
    "exists": true,
    "notFound": false,
    "closed": false,
    "cnt": 0
  },
  "1570651010": {
    "exists": true,
    "notFound": false,
    "closed": false,
    "cnt": 0
  },
  "1573785197": {
    "exists": true,
    "notFound": false,
    "closed": false,
    "cnt": 0
  },
  "1574086767": {
    "exists": true,
    "notFound": false,
    "closed": false,
    "cnt": 477
  },
  "1588796615": {
    "exists": true,
    "notFound": false,
    "closed": false,
    "cnt": 5
  },
  "1592638605": {
    "exists": true,
    "notFound": false,
    "closed": false,
    "cnt": 1400
  },
  "1596707366": {
    "exists": true,
    "notFound": false,
    "closed": false,
    "cnt": 0
  },
  "1598027827": {
    "exists": true,
    "notFound": false,
    "closed": false,
    "cnt": 335
  },
  "1609781870": {
    "exists": true,
    "notFound": false,
    "closed": false,
    "cnt": 969
  },
  "1619030818": {
    "exists": true,
    "notFound": false,
    "closed": false,
    "cnt": 0
  },
  "1623121838": {
    "exists": true,
    "notFound": false,
    "closed": false,
    "cnt": 0
  },
  "1625308923": {
    "exists": true,
    "notFound": false,
    "closed": false,
    "cnt": 0
  },
  "1633349278": {
    "exists": true,
    "notFound": false,
    "closed": false,
    "cnt": 1352
  },
  "1639844567": {
    "exists": true,
    "notFound": false,
    "closed": false,
    "cnt": 8
  },
  "1645037230": {
    "exists": true,
    "notFound": false,
    "closed": false,
    "cnt": 114
  },
  "1647867911": {
    "exists": true,
    "notFound": false,
    "closed": false,
    "cnt": 236
  },
  "1649370754": {
    "exists": true,
    "notFound": false,
    "closed": false,
    "cnt": 0
  },
  "1649510619": {
    "exists": true,
    "notFound": false,
    "closed": false,
    "cnt": 367
  },
  "1652457357": {
    "exists": true,
    "notFound": false,
    "closed": false,
    "cnt": 914
  },
  "1653700335": {
    "exists": true,
    "notFound": false,
    "closed": false,
    "cnt": 0
  },
  "1655236817": {
    "exists": true,
    "notFound": false,
    "closed": false,
    "cnt": 0
  },
  "1658878760": {
    "exists": true,
    "notFound": false,
    "closed": false,
    "cnt": 0
  },
  "1661895314": {
    "exists": true,
    "notFound": false,
    "closed": false,
    "cnt": 4710
  },
  "1670097232": {
    "exists": true,
    "notFound": false,
    "closed": false,
    "cnt": 7
  },
  "1671040223": {
    "exists": true,
    "notFound": false,
    "closed": false,
    "cnt": 144
  },
  "1679798262": {
    "exists": true,
    "notFound": false,
    "closed": false,
    "cnt": 1
  },
  "1701106568": {
    "exists": true,
    "notFound": false,
    "closed": false,
    "cnt": 2522
  },
  "1716496855": {
    "exists": true,
    "notFound": false,
    "closed": false,
    "cnt": 0
  },
  "1720211299": {
    "exists": true,
    "notFound": false,
    "closed": false,
    "cnt": 1244
  },
  "1725571575": {
    "exists": true,
    "notFound": false,
    "closed": false,
    "cnt": 112
  },
  "1728662157": {
    "exists": true,
    "notFound": false,
    "closed": false,
    "cnt": 0
  },
  "1730211041": {
    "exists": true,
    "notFound": false,
    "closed": false,
    "cnt": 0
  },
  "1731282649": {
    "exists": true,
    "notFound": false,
    "closed": false,
    "cnt": 1025
  },
  "1739196774": {
    "exists": true,
    "notFound": false,
    "closed": false,
    "cnt": 0
  },
  "1741084271": {
    "exists": true,
    "notFound": false,
    "closed": false,
    "cnt": 492
  },
  "1741365727": {
    "exists": true,
    "notFound": false,
    "closed": false,
    "cnt": 1358
  },
  "1759367638": {
    "exists": true,
    "notFound": false,
    "closed": false,
    "cnt": 650
  },
  "1761486260": {
    "exists": true,
    "notFound": false,
    "closed": false,
    "cnt": 314
  },
  "1764123330": {
    "exists": true,
    "notFound": false,
    "closed": false,
    "cnt": 0
  },
  "1770252245": {
    "exists": true,
    "notFound": false,
    "closed": false,
    "cnt": 0
  },
  "1772853894": {
    "exists": true,
    "notFound": false,
    "closed": false,
    "cnt": 0
  },
  "1774351027": {
    "exists": true,
    "notFound": false,
    "closed": false,
    "cnt": 0
  },
  "1804165063": {
    "exists": true,
    "notFound": false,
    "closed": false,
    "cnt": 318
  },
  "1811812357": {
    "exists": true,
    "notFound": false,
    "closed": false,
    "cnt": 0
  },
  "1826439184": {
    "exists": true,
    "notFound": false,
    "closed": false,
    "cnt": 205
  },
  "1832777818": {
    "exists": true,
    "notFound": false,
    "closed": false,
    "cnt": 109
  },
  "1833291288": {
    "exists": true,
    "notFound": false,
    "closed": false,
    "cnt": 164
  },
  "1835771863": {
    "exists": true,
    "notFound": false,
    "closed": false,
    "cnt": 358
  },
  "1849856022": {
    "exists": true,
    "notFound": false,
    "closed": false,
    "cnt": 0
  },
  "1850730924": {
    "exists": true,
    "notFound": false,
    "closed": false,
    "cnt": 154
  },
  "1859662219": {
    "exists": true,
    "notFound": false,
    "closed": false,
    "cnt": 0
  },
  "1880314473": {
    "exists": true,
    "notFound": false,
    "closed": false,
    "cnt": 0
  },
  "1884861003": {
    "exists": true,
    "notFound": false,
    "closed": false,
    "cnt": 0
  },
  "1884867771": {
    "exists": true,
    "notFound": false,
    "closed": false,
    "cnt": 0
  },
  "1890135549": {
    "exists": true,
    "notFound": false,
    "closed": false,
    "cnt": 290
  },
  "1894520557": {
    "exists": true,
    "notFound": false,
    "closed": false,
    "cnt": 0
  },
  "1903944967": {
    "exists": true,
    "notFound": false,
    "closed": false,
    "cnt": 824
  },
  "1904819375": {
    "exists": true,
    "notFound": false,
    "closed": false,
    "cnt": 242
  },
  "1911197556": {
    "exists": true,
    "notFound": false,
    "closed": false,
    "cnt": 0
  },
  "1919227837": {
    "exists": true,
    "notFound": false,
    "closed": false,
    "cnt": 252
  },
  "1920231764": {
    "exists": true,
    "notFound": false,
    "closed": false,
    "cnt": 151
  },
  "1930502119": {
    "exists": true,
    "notFound": false,
    "closed": false,
    "cnt": 0
  },
  "1934338605": {
    "exists": true,
    "notFound": false,
    "closed": false,
    "cnt": 0
  },
  "1937039522": {
    "exists": true,
    "notFound": false,
    "closed": false,
    "cnt": 0
  },
  "1951748608": {
    "exists": true,
    "notFound": false,
    "closed": false,
    "cnt": 0
  },
  "1954827143": {
    "exists": true,
    "notFound": false,
    "closed": false,
    "cnt": 551
  },
  "1957440481": {
    "exists": true,
    "notFound": false,
    "closed": false,
    "cnt": 0
  },
  "1965782928": {
    "exists": true,
    "notFound": false,
    "closed": false,
    "cnt": 0
  },
  "1972686876": {
    "exists": true,
    "notFound": false,
    "closed": false,
    "cnt": 214
  },
  "1995013402": {
    "exists": true,
    "notFound": false,
    "closed": false,
    "cnt": 0
  },
  "1996589942": {
    "exists": true,
    "notFound": false,
    "closed": false,
    "cnt": 0
  },
  "2005171231": {
    "exists": true,
    "notFound": false,
    "closed": false,
    "cnt": 0
  },
  "2007695849": {
    "exists": true,
    "notFound": false,
    "closed": false,
    "cnt": 14
  },
  "2010969727": {
    "exists": true,
    "notFound": false,
    "closed": false,
    "cnt": 0
  },
  "2011476153": {
    "exists": true,
    "notFound": false,
    "closed": false,
    "cnt": 14
  },
  "2018331827": {
    "exists": true,
    "notFound": false,
    "closed": false,
    "cnt": 32
  },
  "2020016089": {
    "exists": true,
    "notFound": false,
    "closed": false,
    "cnt": 0
  },
  "2026432599": {
    "exists": true,
    "notFound": false,
    "closed": false,
    "cnt": 0
  },
  "2029633763": {
    "exists": true,
    "notFound": false,
    "closed": false,
    "cnt": 0
  },
  "2029751096": {
    "exists": true,
    "notFound": false,
    "closed": false,
    "cnt": 621
  },
  "2039109487": {
    "exists": true,
    "notFound": false,
    "closed": false,
    "cnt": 4
  },
  "2039378475": {
    "exists": true,
    "notFound": false,
    "closed": false,
    "cnt": 0
  },
  "2039557595": {
    "exists": true,
    "notFound": false,
    "closed": false,
    "cnt": 659
  },
  "2045796163": {
    "exists": true,
    "notFound": false,
    "closed": false,
    "cnt": 0
  },
  "2056840959": {
    "exists": true,
    "notFound": false,
    "closed": false,
    "cnt": 87
  },
  "2059395646": {
    "exists": true,
    "notFound": false,
    "closed": false,
    "cnt": 445
  },
  "2060242741": {
    "exists": true,
    "notFound": false,
    "closed": false,
    "cnt": 5
  },
  "2060426675": {
    "exists": true,
    "notFound": false,
    "closed": false,
    "cnt": 105
  },
  "2061494598": {
    "exists": true,
    "notFound": false,
    "closed": false,
    "cnt": 62
  },
  "2064392403": {
    "exists": true,
    "notFound": false,
    "closed": false,
    "cnt": 1277
  },
  "2068274546": {
    "exists": true,
    "notFound": false,
    "closed": false,
    "cnt": 0
  },
  "2069712667": {
    "exists": true,
    "notFound": false,
    "closed": false,
    "cnt": 0
  },
  "2072538999": {
    "exists": true,
    "notFound": false,
    "closed": false,
    "cnt": 2
  },
  "2073439485": {
    "exists": true,
    "notFound": false,
    "closed": false,
    "cnt": 1272
  },
  "2078298254": {
    "exists": true,
    "notFound": false,
    "closed": false,
    "cnt": 0
  },
  "2079366553": {
    "exists": true,
    "notFound": false,
    "closed": false,
    "cnt": 47
  },
  "2083411628": {
    "exists": true,
    "notFound": false,
    "closed": false,
    "cnt": 1
  },
  "2083745812": {
    "exists": true,
    "notFound": false,
    "closed": false,
    "cnt": 0
  },
  "2084200781": {
    "exists": true,
    "notFound": false,
    "closed": false,
    "cnt": 0
  },
  "2088299587": {
    "exists": true,
    "notFound": false,
    "closed": false,
    "cnt": 0
  },
  "2088607033": {
    "exists": true,
    "notFound": false,
    "closed": false,
    "cnt": 0
  },
  "2090743201": {
    "exists": true,
    "notFound": false,
    "closed": false,
    "cnt": 0
  },
  "2096707217": {
    "exists": true,
    "notFound": false,
    "closed": false,
    "cnt": 0
  },
  "2147366257": {
    "exists": true,
    "notFound": false,
    "closed": false,
    "cnt": 0
  }
}