{
  "id": 26,
  "slug": "gangnam-meat-best-2026",
  "title": "강남역 고기 맛집 추천 7곳 | 2026 가격·평점 비교",
  "description": "강남역 고기집 가이드 — 삼겹살, 한우, 갈비 가격 비교",
  "category": "meat",
  "region": "gangnam",
  "date": "2026-05-13",
  "tags": [],
  "restaurants": [
    {
      "name": "꼬끼오 장작구이",
      "type": "고기구이",
      "addr": "서울특별시 강남구 역삼동 827-46 1, 2층",
      "hours": "",
      "tel": "07-1321-9010",
      "priceRange": "17000~28000",
      "rating": 4.8,
      "reviewCount": 59,
      "blogCount": 710,
      "cat": [
        "한식"
      ],
      "tags": [
        "리뷰많음",
        "가성비",
        "데이트"
      ],
      "keywords": [],
      "moods": [],
      "scene": [],
      "parking": false,
      "reservation": false,
      "menuItems": [
        {
          "name": "한방누룽지통닭",
          "price": 19900,
          "description": ""
        },
        {
          "name": "코리아바베큐통닭",
          "price": 26000,
          "description": ""
        },
        {
          "name": "통통마늘통닭",
          "price": 26000,
          "description": ""
        },
        {
          "name": "콘치즈통닭",
          "price": 26000,
          "description": ""
        },
        {
          "name": "한방누룽지통닭 포장",
          "price": 17500,
          "description": ""
        }
      ],
      "naverUrl": "https://map.naver.com/v5/entry/place/1553521994",
      "imageUrl": "https://search.pstatic.net/common/?autoRotate=true&quality=100&type=f640_380&src=https%3A%2F%2Fldb-phinf.pstatic.net%2F20240426_242%2F1714124019043NbMkY_JPEG%2FIMG_7198.jpeg",
      "imageUrl2": "https://search.pstatic.net/common/?autoRotate=true&type=w560_sharpen&src=https%3A%2F%2Fldb-phinf.pstatic.net%2F20240426_242%2F1714124019043NbMkY_JPEG%2FIMG_7198.jpeg",
      "imageUrl3": "https://search.pstatic.net/common/?autoRotate=true&type=w278_sharpen&src=https%3A%2F%2Fldb-phinf.pstatic.net%2F20240426_4%2F1714124018584ABBYY_JPEG%2FIMG_7197.jpeg",
      "imageUrl4": "https://search.pstatic.net/common/?autoRotate=true&type=w278_sharpen&src=https%3A%2F%2Fldb-phinf.pstatic.net%2F20231119_276%2F1700375488029U9Jk3_JPEG%2F%25B3%25D7%25C0%25CC%25B9%25F6%25C5%25EB%25B4%25DF%25B1%25B8%25C0%25CC4.jpg",
      "imageUrl5": "https://search.pstatic.net/common/?autoRotate=true&type=w278_sharpen&src=https%3A%2F%2Fldb-phinf.pstatic.net%2F20231119_282%2F1700375488049yo3gc_JPEG%2F%25B3%25D7%25C0%25CC%25B9%25F6%25C5%25EB%25B4%25DF%25B1%25B8%25C0%25CC3.jpg",
      "imageUrl6": "https://search.pstatic.net/common/?autoRotate=true&type=w278_sharpen&src=https%3A%2F%2Fldb-phinf.pstatic.net%2F20231119_179%2F1700375488047wOnRn_JPEG%2F%25B3%25D7%25C0%25CC%25B9%25F6%25C5%25EB%25B4%25DF%25B1%25B8%25C0%25CC1.jpg",
      "imageUrl7": "https://ldb-phinf.pstatic.net/20231119_292/17003773740502E9nL_JPEG/%B3%D7%C0%CC%B9%F6%C7%D1%B9%E6%C5%EB%B4%DF.jpg",
      "imageUrl8": "https://ldb-phinf.pstatic.net/20250912_44/1757665212661GO8b2_JPEG/1757664712992.jpg",
      "region": "gangnam",
      "regionName": "강남역",
      "regionPath": "/dinner/gangnam",
      "emoji": ""
    },
    {
      "name": "고기꾼김춘배 강남점",
      "type": "고기구이",
      "addr": "서울특별시 강남구 역삼동 619-5 3층, 4층",
      "hours": "22:30에 영업 종료",
      "tel": "07-1342-5659",
      "priceRange": "8000~34000",
      "rating": 4.8,
      "reviewCount": 59,
      "blogCount": 2001,
      "cat": [
        "고기구이"
      ],
      "tags": [
        "리뷰많음",
        "주차가능",
        "단체가능",
        "데이트",
        "예약필수"
      ],
      "keywords": [],
      "moods": [],
      "scene": [],
      "parking": true,
      "reservation": true,
      "menuItems": [
        {
          "name": "한우 꾸리살 육회 200g",
          "price": 28000,
          "description": ""
        },
        {
          "name": "국내산生 오겹살 150g",
          "price": 17000,
          "description": ""
        },
        {
          "name": "국내산生목살 180g",
          "price": 17000,
          "description": ""
        },
        {
          "name": "Prime 본갈비살 150g",
          "price": 33000,
          "description": ""
        },
        {
          "name": "반반냉면",
          "price": 8000,
          "description": ""
        }
      ],
      "naverUrl": "https://map.naver.com/v5/entry/place/37837518",
      "imageUrl": "https://search.pstatic.net/common/?autoRotate=true&quality=100&type=f640_380&src=https%3A%2F%2Fldb-phinf.pstatic.net%2F20251223_12%2F1766465054437g40JH_JPEG%2F%25BD%25E6%25B3%25D7%25C0%25CF.jpg",
      "imageUrl2": "https://search.pstatic.net/common/?autoRotate=true&type=w560_sharpen&src=https%3A%2F%2Fldb-phinf.pstatic.net%2F20251223_12%2F1766465054437g40JH_JPEG%2F%25BD%25E6%25B3%25D7%25C0%25CF.jpg",
      "imageUrl3": "https://search.pstatic.net/common/?autoRotate=true&type=w278_sharpen&src=https%3A%2F%2Fldb-phinf.pstatic.net%2F20251223_78%2F176646505517018SqA_PNG%2FKakaoTalk_20251222_110957879_01.png",
      "imageUrl4": "https://search.pstatic.net/common/?autoRotate=true&type=w278_sharpen&src=https%3A%2F%2Fldb-phinf.pstatic.net%2F20251223_34%2F17664650553738y7UV_JPEG%2FKakaoTalk_20251222_110957879_02.jpg",
      "imageUrl5": "https://search.pstatic.net/common/?autoRotate=true&type=w278_sharpen&src=https%3A%2F%2Fldb-phinf.pstatic.net%2F20251223_91%2F1766465055304F8teW_JPEG%2FKakaoTalk_20251222_110957879_05.jpg",
      "imageUrl6": "https://search.pstatic.net/common/?autoRotate=true&type=w278_sharpen&src=https%3A%2F%2Fldb-phinf.pstatic.net%2F20251223_32%2F1766465055394uCT2f_JPEG%2FKakaoTalk_20251222_110957879.jpg",
      "imageUrl7": "https://ldb-phinf.pstatic.net/20250323_117/1742723623531BP6DB_JPEG/KakaoTalk_20250323_184834419.jpg",
      "imageUrl8": "https://ldb-phinf.pstatic.net/20241022_134/1729588551532mRG1v_JPEG/%BF%C0%B0%E3%BB%EC.jpg",
      "region": "gangnam",
      "regionName": "강남역",
      "regionPath": "/dinner/gangnam",
      "emoji": ""
    },
    {
      "name": "까사생갈비",
      "type": "고기구이",
      "addr": "서울특별시 강남구 역삼동 810-7 2층 까사생갈비",
      "hours": "",
      "tel": "07-1384-5705",
      "priceRange": "5000~109000",
      "rating": 4.8,
      "reviewCount": 59,
      "blogCount": 1556,
      "cat": [
        "고기구이"
      ],
      "tags": [
        "리뷰많음",
        "주차가능",
        "단체가능",
        "데이트",
        "예약필수"
      ],
      "keywords": [],
      "moods": [],
      "scene": [],
      "parking": true,
      "reservation": true,
      "menuItems": [
        {
          "name": "프리미엄 숙성 생갈비",
          "price": 18000,
          "description": ""
        },
        {
          "name": "이베리코 베요타 목살",
          "price": 20000,
          "description": ""
        },
        {
          "name": "숙성 삼겹살",
          "price": 18000,
          "description": ""
        },
        {
          "name": "황제 소 꽃갈비",
          "price": 39000,
          "description": ""
        },
        {
          "name": "돼지모듬 세트[신논현역맛집대표메뉴]",
          "price": 89000,
          "description": ""
        }
      ],
      "naverUrl": "https://map.naver.com/v5/entry/place/593588180",
      "imageUrl": "https://search.pstatic.net/common/?autoRotate=true&quality=100&type=f640_380&src=https%3A%2F%2Fldb-phinf.pstatic.net%2F20210706_274%2F1625562793688SfwWj_JPEG%2FU4RTD0d4QYMco5KkpBHLMdG9.jpg",
      "imageUrl2": "https://search.pstatic.net/common/?autoRotate=true&type=w560_sharpen&src=https%3A%2F%2Fldb-phinf.pstatic.net%2F20210706_274%2F1625562793688SfwWj_JPEG%2FU4RTD0d4QYMco5KkpBHLMdG9.jpg",
      "imageUrl3": "https://search.pstatic.net/common/?autoRotate=true&type=w278_sharpen&src=https%3A%2F%2Fldb-phinf.pstatic.net%2F20210706_113%2F1625562808660A1Frt_JPEG%2Fz37-5l5JtCAQ6boi00oPh7IT.jpg",
      "imageUrl4": "https://search.pstatic.net/common/?autoRotate=true&type=w278_sharpen&src=https%3A%2F%2Fldb-phinf.pstatic.net%2F20210706_38%2F1625562839620KLbBM_JPEG%2FtYW4BOLKaVODznSrH-hI-V4D.jpg",
      "imageUrl5": "https://search.pstatic.net/common/?autoRotate=true&type=w278_sharpen&src=https%3A%2F%2Fldb-phinf.pstatic.net%2F20210706_186%2F1625562853343a5Gnp_JPEG%2F79jA4weeq8Rc7DHIjJPR5qME.jpg",
      "imageUrl6": "https://search.pstatic.net/common/?autoRotate=true&type=w278_sharpen&src=https%3A%2F%2Fldb-phinf.pstatic.net%2F20230213_73%2F16762648018520KBuV_JPEG%2F%25B0%25A3%25C6%25C7.jpg",
      "imageUrl7": "https://ldb-phinf.pstatic.net/20230403_109/1680509684133DFLdX_JPEG/%BB%FD%B0%A5%BA%F1_%BA%B8%C1%A4.jpg",
      "imageUrl8": "https://ldb-phinf.pstatic.net/20230403_54/1680509741090hWFTk_JPEG/%B8%F1%BB%EC_%BA%B8%C1%A4.jpg",
      "region": "gangnam",
      "regionName": "강남역",
      "regionPath": "/dinner/gangnam",
      "emoji": ""
    },
    {
      "name": "전설의우대갈비 강남직영점",
      "type": "고기구이",
      "addr": "서울특별시 강남구 역삼동 819 3층 1호",
      "hours": "11:10에 영업 시작",
      "tel": "07-1420-9050",
      "priceRange": "22000~39000",
      "rating": 4.8,
      "reviewCount": 59,
      "blogCount": 1163,
      "cat": [
        "고기구이"
      ],
      "tags": [
        "리뷰많음",
        "주차가능",
        "예약필수"
      ],
      "keywords": [],
      "moods": [],
      "scene": [],
      "parking": true,
      "reservation": true,
      "menuItems": [
        {
          "name": "전설우대갈비(1대) 370g",
          "price": 39000,
          "description": ""
        },
        {
          "name": "[평일] 소갈비살 정식 [Lunch]",
          "price": 28000,
          "description": ""
        },
        {
          "name": "전설소갈비살 160g",
          "price": 26000,
          "description": ""
        },
        {
          "name": "전설소막창 200g",
          "price": 29000,
          "description": ""
        },
        {
          "name": "전설삼겹살 200g",
          "price": 22000,
          "description": ""
        }
      ],
      "naverUrl": "https://map.naver.com/v5/entry/place/1060344271",
      "imageUrl": "https://search.pstatic.net/common/?autoRotate=true&quality=100&type=f640_380&src=https%3A%2F%2Fldb-phinf.pstatic.net%2F20250224_95%2F1740380218515lq6OR_PNG%2F%25B8%25DE%25C0%25CE1.png",
      "imageUrl2": "https://search.pstatic.net/common/?autoRotate=true&type=w560_sharpen&src=https%3A%2F%2Fldb-phinf.pstatic.net%2F20250224_95%2F1740380218515lq6OR_PNG%2F%25B8%25DE%25C0%25CE1.png",
      "imageUrl3": "https://search.pstatic.net/common/?autoRotate=true&type=w278_sharpen&src=https%3A%2F%2Fldb-phinf.pstatic.net%2F20250224_210%2F1740380217783EkMt4_PNG%2F%25B8%25DE%25C0%25CE2.png",
      "imageUrl4": "https://search.pstatic.net/common/?autoRotate=true&type=w278_sharpen&src=https%3A%2F%2Fldb-phinf.pstatic.net%2F20250224_233%2F1740380217817jT5uR_PNG%2F%25B8%25DE%25C0%25CE3.png",
      "imageUrl5": "https://search.pstatic.net/common/?autoRotate=true&type=w278_sharpen&src=https%3A%2F%2Fldb-phinf.pstatic.net%2F20221220_199%2F1671523028789N0Brm_JPEG%2FKakaoTalk_20210317_095028746.jpg",
      "imageUrl6": "https://search.pstatic.net/common/?autoRotate=true&type=w278_sharpen&src=https%3A%2F%2Fldb-phinf.pstatic.net%2F20221220_146%2F1671523053564pzasF_JPEG%2F4.jpg",
      "imageUrl7": "https://ldb-phinf.pstatic.net/20260127_124/1769489279575O6Yl7_PNG/%C0%FC%BC%B3%BF%EC%B4%EB%B0%A5%BA%F1.png",
      "imageUrl8": "https://ldb-phinf.pstatic.net/20260127_195/1769489291551xBKUC_PNG/%BC%D2%B0%A5%BA%F1%BB%EC%B7%B1%C4%A1%B5%C8%C0%E5%C2%EE%B0%B3.png",
      "region": "gangnam",
      "regionName": "강남역",
      "regionPath": "/dinner/gangnam",
      "emoji": ""
    },
    {
      "name": "라장양갈비양꼬치 무한리필",
      "type": "고기구이",
      "addr": "서울특별시 강남구 역삼동 619-30 지상3층",
      "hours": "23:30에 영업 종료",
      "tel": "07-1345-6758",
      "priceRange": "15000~27900",
      "rating": 4.8,
      "reviewCount": 59,
      "blogCount": 1521,
      "cat": [
        "중식"
      ],
      "tags": [
        "리뷰많음",
        "가성비",
        "단체가능",
        "웨이팅맛집"
      ],
      "keywords": [],
      "moods": [],
      "scene": [],
      "parking": false,
      "reservation": false,
      "menuItems": [
        {
          "name": "양꼬치 무한리필",
          "price": 23900,
          "description": ""
        },
        {
          "name": "양어깨등심+양꼬치+식사류 (무한리필)",
          "price": 25900,
          "description": ""
        },
        {
          "name": "양갈비+양꼬치+요리1개+식사 무한리필",
          "price": 27900,
          "description": ""
        },
        {
          "name": "양꼬치",
          "price": 15000,
          "description": ""
        },
        {
          "name": "생양갈비(숄더랙)",
          "price": 24000,
          "description": ""
        }
      ],
      "naverUrl": "https://map.naver.com/v5/entry/place/1037655034",
      "imageUrl": "https://search.pstatic.net/common/?autoRotate=true&quality=100&type=f640_380&src=https%3A%2F%2Fldb-phinf.pstatic.net%2F20231226_201%2F1703558043886LdPbH_JPEG%2FKakaoTalk_20231226_110025920.jpg",
      "imageUrl2": "https://search.pstatic.net/common/?autoRotate=true&type=w560_sharpen&src=https%3A%2F%2Fldb-phinf.pstatic.net%2F20231226_201%2F1703558043886LdPbH_JPEG%2FKakaoTalk_20231226_110025920.jpg",
      "imageUrl3": "https://search.pstatic.net/common/?autoRotate=true&type=w278_sharpen&src=https%3A%2F%2Fldb-phinf.pstatic.net%2F20231227_293%2F1703640531649wItpq_JPEG%2FKakaoTalk_20231226_163154361_03.jpg",
      "imageUrl4": "https://search.pstatic.net/common/?autoRotate=true&type=w278_sharpen&src=https%3A%2F%2Fldb-phinf.pstatic.net%2F20231227_95%2F1703640531611nIJqw_JPEG%2FKakaoTalk_20231226_163154361_01.jpg",
      "imageUrl5": "https://search.pstatic.net/common/?autoRotate=true&type=w278_sharpen&src=https%3A%2F%2Fldb-phinf.pstatic.net%2F20231227_239%2F17036405315993j7Tq_JPEG%2FKakaoTalk_20231226_163154361.jpg",
      "imageUrl6": "https://search.pstatic.net/common/?autoRotate=true&type=w278_sharpen&src=https%3A%2F%2Fldb-phinf.pstatic.net%2F20231226_260%2F1703558043504uG3pI_JPEG%2FKakaoTalk_20231226_110025920_01.jpg",
      "imageUrl7": "https://ldb-phinf.pstatic.net/20240102_61/1704172960354PIhiv_PNG/20240102142304.png",
      "imageUrl8": "https://ldb-phinf.pstatic.net/20240102_21/1704171265783JTTnC_JPEG/KakaoTalk_20231226_110025920.jpg",
      "region": "gangnam",
      "regionName": "강남역",
      "regionPath": "/dinner/gangnam",
      "emoji": ""
    },
    {
      "name": "칼맞은삼겹살 강남본점",
      "type": "고기구이",
      "addr": "서울특별시 서초구 서초동 1308-14 1층 칼맞은삼겹살",
      "hours": "",
      "tel": "02-533-7732",
      "priceRange": "",
      "rating": 4.8,
      "reviewCount": 6,
      "blogCount": 0,
      "cat": [
        "고기구이"
      ],
      "tags": [],
      "keywords": [],
      "moods": [],
      "scene": [],
      "parking": false,
      "reservation": false,
      "menuItems": [],
      "naverUrl": "https://map.naver.com/v5/entry/place/702447560",
      "imageUrl": "https://search.pstatic.net/common/?autoRotate=true&quality=100&type=f640_380&src=https%3A%2F%2Fldb-phinf.pstatic.net%2F20220913_192%2F1663056263581LQk4y_JPEG%2Fimage.jpg",
      "imageUrl2": "https://search.pstatic.net/common/?autoRotate=true&type=w560_sharpen&src=https%3A%2F%2Fldb-phinf.pstatic.net%2F20220913_192%2F1663056263581LQk4y_JPEG%2Fimage.jpg",
      "imageUrl3": "https://search.pstatic.net/common/?autoRotate=true&type=w278_sharpen&src=https%3A%2F%2Fldb-phinf.pstatic.net%2F20200526_205%2F1590494180729BLKuj_JPEG%2Ff27whZa71dxlREI6q0Vv369f.jpg",
      "imageUrl4": "https://search.pstatic.net/common/?autoRotate=true&type=w278_sharpen&src=https%3A%2F%2Fldb-phinf.pstatic.net%2F20230111_98%2F1673414014041Js2SL_JPEG%2F20221231_091002.jpg",
      "imageUrl5": "https://search.pstatic.net/common/?autoRotate=true&type=w278_sharpen&src=https%3A%2F%2Fpup-review-phinf.pstatic.net%2FMjAyNTEwMjBfNjQg%2FMDAxNzYwOTYzNzU4MzI2.jFQMNn8Vmc3r407PrWnqbNcIC9hemi4-ckJ_BcpQZlMg.DzU1wJIjc3t1o1DVjaAgSi4JHZC22QyimKNeGQWCeyMg.JPEG%2F93BFD7D6-EF1A-4548-866B-271D4D1A49A0.jpeg",
      "imageUrl6": "https://search.pstatic.net/common/?autoRotate=true&type=w278_sharpen&src=https%3A%2F%2Fpup-review-phinf.pstatic.net%2FMjAyNTA4MTZfMjcx%2FMDAxNzU1MzEyNTY4NDU5.mS2ZUOiOmjBjLT2MJU2-t0Y7XpgNLXeTXRBAueruftAg.NxQv9PC8fSlLIEFQ9SqxNaqX79GHVuQPmxqtUr-_nCYg.JPEG%2FB0713374-CA86-45A1-8297-25B03341B07A.jpeg",
      "imageUrl7": "https://ldb-phinf.pstatic.net/20220913_204/1663057168991bbYSh_PNG/AA1F1E28-1360-4767-9482-482E69BFC362.png",
      "imageUrl8": "https://ldb-phinf.pstatic.net/20230619_176/1687165207878ziXpg_JPEG/IMG_7724.jpeg",
      "region": "gangnam",
      "regionName": "강남역",
      "regionPath": "/dinner/gangnam",
      "emoji": ""
    },
    {
      "name": "엄순녀뼈구이순대국 강남역점",
      "type": "고기구이",
      "addr": "서울특별시 강남구 역삼동 817-5 지상 1층, 2층",
      "hours": "",
      "tel": "02-6448-6110",
      "priceRange": "10000~34000",
      "rating": 0,
      "reviewCount": 475,
      "blogCount": 0,
      "cat": [
        "한식"
      ],
      "tags": [],
      "keywords": [],
      "moods": [],
      "scene": [],
      "parking": false,
      "reservation": false,
      "menuItems": [
        {
          "name": "숯불뼈구이세트(2인이상주문)",
          "price": 15000,
          "description": ""
        },
        {
          "name": "치즈뼈구이세트(2인이상주문)",
          "price": 15000,
          "description": ""
        },
        {
          "name": "돼지한마리 얼큰해장순대국",
          "price": 11000,
          "description": ""
        },
        {
          "name": "로제뼈구이세트(2인이상주문)",
          "price": 15000,
          "description": ""
        },
        {
          "name": "우거지감자탕(소/중/대)",
          "price": 34000,
          "description": ""
        }
      ],
      "naverUrl": "https://map.naver.com/v5/entry/place/2083281149",
      "imageUrl": "https://search.pstatic.net/common/?autoRotate=true&quality=100&type=f640_380&src=https%3A%2F%2Fldb-phinf.pstatic.net%2F20251119_74%2F1763538704899okiVv_PNG%2F%25C4%25A1%25C1%25EE%25BB%25C0%25B1%25B8%25C0%25CC%25B1%25D9%25C1%25A2.png",
      "imageUrl2": "https://search.pstatic.net/common/?autoRotate=true&type=w560_sharpen&src=https%3A%2F%2Fldb-phinf.pstatic.net%2F20251119_74%2F1763538704899okiVv_PNG%2F%25C4%25A1%25C1%25EE%25BB%25C0%25B1%25B8%25C0%25CC%25B1%25D9%25C1%25A2.png",
      "imageUrl3": "https://search.pstatic.net/common/?autoRotate=true&type=w278_sharpen&src=https%3A%2F%2Fnaverbooking-phinf.pstatic.net%2F20251106_77%2F1762394521544mQ672_PNG%2F%25BE%25F6%25BC%25F8%25B3%25E0_%25B3%25D7%25BF%25C21-1_%25C0%25FA%25C8%25AD%25C1%25FA.png",
      "imageUrl4": "https://search.pstatic.net/common/?autoRotate=true&type=w278_sharpen&src=https%3A%2F%2Fldb-phinf.pstatic.net%2F20250716_54%2F1752653537956Bv4mw_JPEG%2FKakaoTalk_20250613_135213155_19.jpg",
      "imageUrl5": "https://search.pstatic.net/common/?autoRotate=true&type=w278_sharpen&src=https%3A%2F%2Fldb-phinf.pstatic.net%2F20251119_300%2F1763538591294Nj1cp_PNG%2F%25BE%25F6%25BC%25F8%25B3%25E0_%25B3%25D7%25BF%25C22-1_%25C0%25FA%25C8%25AD%25C1%25FA.png",
      "imageUrl6": "https://search.pstatic.net/common/?autoRotate=true&type=w278_sharpen&src=https%3A%2F%2Fldb-phinf.pstatic.net%2F20250813_23%2F1755060562067Bfoy9_JPEG%2F%25BD%25A1%25BA%25D2%25BB%25C0%25B1%25B8%25C0%25CC%25284%25C0%25CE%2529.jpg",
      "imageUrl7": "https://ldb-phinf.pstatic.net/20250813_79/1755045348772t3gzi_JPEG/%BD%A1%BA%D2%BB%C0%B1%B8%C0%CC%283%C0%CE%29.jpg",
      "imageUrl8": "https://ldb-phinf.pstatic.net/20250813_120/17550540073781tcys_JPEG/%BD%A1%BA%D2%BB%C0%B1%B8%C0%CC%283%C0%CE%29_%C4%A1%C1%EE.jpg",
      "region": "gangnam",
      "regionName": "강남역",
      "regionPath": "/dinner/gangnam",
      "emoji": ""
    }
  ],
  "categoryStats": {},
  "regionTotalRestaurants": 285
}